colortty/__init__.py
colortty/_colortty.py
colortty-0.1.0.dist-info/licenses/LICENSE
colortty-0.1.0.dist-info/METADATA
colortty-0.1.0.dist-info/WHEEL
colortty-0.1.0.dist-info/top_level.txt
colortty-0.1.0.dist-info/RECORD
