Metadata-Version: 2.4
Name: colortty
Version: 0.1.0
Summary: Terminal color styling: compose ANSI escapes for foreground/background and text attributes.
Author-email: Ruilx <RuilxAlxa@qq.com>
License: MIT
Project-URL: Homepage, https://github.com/Ruilx/colortty
Project-URL: Repository, https://github.com/Ruilx/colortty
Keywords: ansi,color,terminal,tty,style
Classifier: License :: OSI Approved :: MIT License
Classifier: Programming Language :: Python :: 3 :: Only
Classifier: Programming Language :: Python :: 3.11
Classifier: Intended Audience :: Developers
Classifier: Topic :: Terminals
Requires-Python: >=3.11
License-File: LICENSE
Dynamic: license-file
